{"cameraMode":{"drawMode":0,"name":"Shaded","section":"Shading Mode"},"sceneLighting":true,"audioPlay":false,"sceneViewState":{"showFog":true,"showMaterialUpdate":false,"showSkybox":true,"showFlares":true,"showImageEffects":false,"showParticleSystems":true,"showVisualEffectGraphs":true,"m_FxEnabled":true},"in2DMode":false,"pivot":{"x":-6.635203838348389,"y":0.07713179290294647,"z":3.3868298530578615},"rotation":{"x":0.15882524847984315,"y":-0.7923815846443176,"z":0.2323860079050064,"w":0.5414161682128906},"size":4.0,"orthographic":false}